asyncio_advanced_semaphores/__init__.py
asyncio_advanced_semaphores/common.py
asyncio_advanced_semaphores/memory/README.md
asyncio_advanced_semaphores/memory/__init__.py
asyncio_advanced_semaphores/memory/queue.py
asyncio_advanced_semaphores/memory/sem.py
asyncio_advanced_semaphores/py.typed
asyncio_advanced_semaphores/redis/README.md
asyncio_advanced_semaphores/redis/__init__.py
asyncio_advanced_semaphores/redis/client.py
asyncio_advanced_semaphores/redis/conf.py
asyncio_advanced_semaphores/redis/lua/README.md
asyncio_advanced_semaphores/redis/lua/__init__.py
asyncio_advanced_semaphores/redis/lua/acquire.lua
asyncio_advanced_semaphores/redis/lua/card.lua
asyncio_advanced_semaphores/redis/lua/ping.lua
asyncio_advanced_semaphores/redis/lua/queue.lua
asyncio_advanced_semaphores/redis/lua/release.lua
asyncio_advanced_semaphores/redis/lua/wake_up_nexts.lua
asyncio_advanced_semaphores/redis/sem.py
asyncio_advanced_semaphores-0.0.7.dist-info/WHEEL
asyncio_advanced_semaphores-0.0.7.dist-info/METADATA
asyncio_advanced_semaphores-0.0.7.dist-info/RECORD
