Metadata-Version: 2.3
Name: asyncio-advanced-semaphores
Version: 0.0.7
Summary: Add your description here
Requires-Dist: redis>=7.1.0
Requires-Dist: stlog>=0.5.0
Requires-Dist: tenacity>=9.1.2
Requires-Python: >=3.12
